[{
  "_id": {
    "$oid": "5f808b7882390000ac005c42"
  },
  "from": 1,
  "to": 3,
  "message": "Lorem ispum",
  "is_read": "0"
},{
  "_id": {
    "$oid": "5f808b7882390000ac005c43"
  },
  "from": 1,
  "to": 2,
  "message": "Lorem ispum",
  "is_read": "0"
},{
  "_id": {
    "$oid": "5f82f459bbe4f3e2d2e052e1"
  },
  "from": 2,
  "to": 1,
  "message": "Lorem ispum 2",
  "is_read": 1
},{
  "_id": {
    "$oid": "5f8302e6de78000074003f65"
  },
  "from": 1,
  "to": 2,
  "message": "ABC",
  "is_read": 1
},{
  "_id": {
    "$oid": "5f830657de78000074003f66"
  },
  "from": 1,
  "to": 2,
  "message": "abc",
  "is_read": 1
},{
  "_id": {
    "$oid": "5f83070ede78000074003f67"
  },
  "from": 1,
  "to": 2,
  "message": "Nguyen Van Hai",
  "is_read": 1
},{
  "_id": {
    "$oid": "5f830a95de78000074003f68"
  },
  "from": 1,
  "to": 2,
  "message": "Try my best",
  "is_read": 1
},{
  "_id": {
    "$oid": "5f83958f207400000a002ce5"
  },
  "from": 1,
  "to": 2,
  "message": "I'm feeling so bad",
  "is_read": 1
},{
  "_id": {
    "$oid": "5f839da9207400000a002ce8"
  },
  "from": 1,
  "to": 2,
  "message": "abc",
  "is_read": 1
},{
  "_id": {
    "$oid": "5f839dde207400000a002ce9"
  },
  "from": 1,
  "to": 2,
  "message": "abcxyz",
  "is_read": 1
},{
  "_id": {
    "$oid": "5f839f4a207400000a002cec"
  },
  "from": 1,
  "to": 2,
  "message": "PTT",
  "is_read": 1
},{
  "_id": {
    "$oid": "5f839f4e207400000a002ced"
  },
  "from": 1,
  "to": 2,
  "message": "PTT",
  "is_read": 1
},{
  "_id": {
    "$oid": "5f839fd0207400000a002cee"
  },
  "from": 1,
  "to": 2,
  "message": "abc",
  "is_read": 1
},{
  "_id": {
    "$oid": "5f83e5fa207400000a002cef"
  },
  "from": 1,
  "to": 2,
  "message": "Test",
  "is_read": 1
},{
  "_id": {
    "$oid": "5f83e619207400000a002cf0"
  },
  "from": 1,
  "to": 2,
  "message": "Test new",
  "is_read": 1
},{
  "_id": {
    "$oid": "5f83e9b75dc03b666d9cd33f"
  },
  "from": "2",
  "is_read": 1,
  "to": 1
},{
  "_id": {
    "$oid": "5f83eb33207400000a002cf1"
  },
  "from": 1,
  "to": 2,
  "message": "abc",
  "is_read": 1
},{
  "_id": {
    "$oid": "5f88539e0449000038000f67"
  },
  "from": 1,
  "to": 2,
  "message": "Nguyen Van Hai",
  "is_read": 1
},{
  "_id": {
    "$oid": "5f8eef8d510d00003e007736"
  },
  "from": 1,
  "to": 2,
  "message": "abc",
  "is_read": 1
},{
  "_id": {
    "$oid": "5f94dfbe0652000060004405"
  },
  "from": 2,
  "to": 1,
  "message": "hai",
  "is_read": 1
},{
  "_id": {
    "$oid": "5f94e0e10652000060004406"
  },
  "from": 2,
  "to": 1,
  "message": "Nguyen Van Hai",
  "is_read": 1
},{
  "_id": {
    "$oid": "5f94e13b0652000060004407"
  },
  "from": 2,
  "to": 1,
  "message": "ha",
  "is_read": 1
},{
  "_id": {
    "$oid": "5f94e1c90652000060004408"
  },
  "from": 2,
  "to": 1,
  "message": "ha",
  "is_read": 1
},{
  "_id": {
    "$oid": "5f94e25c0652000060004409"
  },
  "from": 2,
  "to": 1,
  "message": "wtf",
  "is_read": 1
},{
  "_id": {
    "$oid": "5f94e56c065200006000440a"
  },
  "from": 2,
  "to": 1,
  "message": "em be",
  "is_read": 1
},{
  "_id": {
    "$oid": "5f94e5d9065200006000440b"
  },
  "from": 2,
  "to": 1,
  "message": "nguyenvanhai",
  "is_read": 1
},{
  "_id": {
    "$oid": "5f94e61b065200006000440c"
  },
  "from": 2,
  "to": 1,
  "message": "abs",
  "is_read": 1
},{
  "_id": {
    "$oid": "5f954f0cf21000008f001ab7"
  },
  "from": 2,
  "to": 1,
  "message": "anh",
  "is_read": 1
},{
  "_id": {
    "$oid": "5f95549ef21000008f001ab8"
  },
  "from": 2,
  "to": 1,
  "message": "alo",
  "is_read": 1
},{
  "_id": {
    "$oid": "5f9554fdf21000008f001ab9"
  },
  "from": 2,
  "to": 1,
  "message": "nghe",
  "is_read": 1
},{
  "_id": {
    "$oid": "5f95550df21000008f001aba"
  },
  "from": 2,
  "to": 1,
  "message": "nghe",
  "is_read": 1
},{
  "_id": {
    "$oid": "5f955c4c2549000042003809"
  },
  "from": 2,
  "to": 1,
  "message": "abc",
  "is_read": 1
},{
  "_id": {
    "$oid": "5f955ce4254900004200380a"
  },
  "from": 2,
  "to": 1,
  "message": "xyz",
  "is_read": 1
},{
  "_id": {
    "$oid": "5f964053d63200004d00383b"
  },
  "from": 2,
  "to": 1,
  "message": "a",
  "is_read": 1
},{
  "_id": {
    "$oid": "5f9641c9d63200004d00383c"
  },
  "from": 1,
  "to": 2,
  "message": "a",
  "is_read": 1
},{
  "_id": {
    "$oid": "5f9641dad63200004d00383d"
  },
  "from": 1,
  "to": 1,
  "message": "a",
  "is_read": 1
},{
  "_id": {
    "$oid": "5f9641dbd63200004d00383e"
  },
  "from": 1,
  "to": 2,
  "message": "a",
  "is_read": 1
},{
  "_id": {
    "$oid": "5f9641dcd63200004d00383f"
  },
  "from": 1,
  "to": 2,
  "message": "a",
  "is_read": 1
},{
  "_id": {
    "$oid": "5f964642d63200004d003844"
  },
  "from": 1,
  "to": 2,
  "message": "k",
  "is_read": 1
},{
  "_id": {
    "$oid": "5f964643d63200004d003845"
  },
  "from": 1,
  "to": 2,
  "message": "k",
  "is_read": 1
},{
  "_id": {
    "$oid": "5f964644d63200004d003846"
  },
  "from": 1,
  "to": 2,
  "message": "k",
  "is_read": 1
},{
  "_id": {
    "$oid": "5f96464ad63200004d003847"
  },
  "from": 1,
  "to": 2,
  "message": "k",
  "is_read": 1
},{
  "_id": {
    "$oid": "5f964672d63200004d003848"
  },
  "from": 1,
  "to": 2,
  "message": "wtf",
  "is_read": 1
},{
  "_id": {
    "$oid": "5f964673d63200004d003849"
  },
  "from": 1,
  "to": 2,
  "message": "wtf",
  "is_read": 1
},{
  "_id": {
    "$oid": "5f964674d63200004d00384a"
  },
  "from": 1,
  "to": 2,
  "message": "wtf",
  "is_read": 1
},{
  "_id": {
    "$oid": "5f96a221de7c00005c001b95"
  },
  "from": 1,
  "to": 2,
  "message": "xyz ne",
  "is_read": 1
},{
  "_id": {
    "$oid": "5f96a222de7c00005c001b96"
  },
  "from": 1,
  "to": 2,
  "message": "xyz ne",
  "is_read": 1
},{
  "_id": {
    "$oid": "5f96a223de7c00005c001b99"
  },
  "from": 1,
  "to": 2,
  "message": "xyz ne",
  "is_read": 1
},{
  "_id": {
    "$oid": "5f96a224de7c00005c001b9c"
  },
  "from": 1,
  "to": 2,
  "message": "xyz ne",
  "is_read": 1
},{
  "_id": {
    "$oid": "5f96a225de7c00005c001b9f"
  },
  "from": 1,
  "to": 2,
  "message": "xyz ne",
  "is_read": 1
},{
  "_id": {
    "$oid": "5f96a226de7c00005c001ba2"
  },
  "from": 1,
  "to": 2,
  "message": "xyz ne",
  "is_read": 1
},{
  "_id": {
    "$oid": "5f96a28bde7c00005c001ba3"
  },
  "from": 1,
  "to": 2,
  "message": "abc",
  "is_read": 1
},{
  "_id": {
    "$oid": "5f96a28cde7c00005c001ba4"
  },
  "from": 1,
  "to": 2,
  "message": "abc",
  "is_read": 1
},{
  "_id": {
    "$oid": "5f96a805de7c00005c001ba5"
  },
  "from": 1,
  "to": 1,
  "message": "a",
  "is_read": 1
},{
  "_id": {
    "$oid": "5f96ad0dde7c00005c001ba6"
  },
  "from": 1,
  "to": 1,
  "message": "abc",
  "is_read": 1
},{
  "_id": {
    "$oid": "5f96b22cde7c00005c001ba7"
  },
  "from": 1,
  "to": 1,
  "message": "anhem",
  "is_read": 1
},{
  "_id": {
    "$oid": "5f96b23bde7c00005c001ba8"
  },
  "from": 1,
  "to": 2,
  "message": "anhem",
  "is_read": 1
},{
  "_id": {
    "$oid": "5f96b29fde7c00005c001ba9"
  },
  "from": 1,
  "to": 2,
  "message": "ilv",
  "is_read": 1
},{
  "_id": {
    "$oid": "5f96b36ede7c00005c001baa"
  },
  "from": 1,
  "to": 2,
  "message": "ilvll",
  "is_read": 1
},{
  "_id": {
    "$oid": "5f96b4fade7c00005c001bab"
  },
  "from": 1,
  "to": 1,
  "message": "abc",
  "is_read": 1
},{
  "_id": {
    "$oid": "5f96b501de7c00005c001bac"
  },
  "from": 1,
  "to": 2,
  "message": "abc",
  "is_read": 1
},{
  "_id": {
    "$oid": "5f96bf17de7c00005c001bad"
  },
  "from": 1,
  "to": 2,
  "message": "i like you",
  "is_read": 1
},{
  "_id": {
    "$oid": "5f96bf91de7c00005c001bae"
  },
  "from": 1,
  "to": 2,
  "message": "do you like me",
  "is_read": 1
},{
  "_id": {
    "$oid": "5f96c077de7c00005c001baf"
  },
  "from": 1,
  "to": 2,
  "message": "fuck",
  "is_read": 1
},{
  "_id": {
    "$oid": "5f96c1d1de7c00005c001bb0"
  },
  "from": 1,
  "to": 2,
  "message": "a",
  "is_read": 1
},{
  "_id": {
    "$oid": "5f96c220de7c00005c001bb1"
  },
  "from": 1,
  "to": 2,
  "message": "a",
  "is_read": 1
},{
  "_id": {
    "$oid": "5f96c92ade7c00005c001bb2"
  },
  "from": 1,
  "to": 2,
  "message": "alo",
  "is_read": 1
},{
  "_id": {
    "$oid": "5f96c9e4de7c00005c001bb3"
  },
  "from": 1,
  "to": 2,
  "message": "abc",
  "is_read": 1
},{
  "_id": {
    "$oid": "5f96c9fdde7c00005c001bb4"
  },
  "from": 1,
  "to": 2,
  "message": "abc",
  "is_read": 0
}]